PyRP1210/RP1210.py
PyRP1210/RP1210Functions.py
PyRP1210/RP1210Select.py
PyRP1210/__init__.py
PYRP1210-1.0.0.dist-info/LICENSE
PYRP1210-1.0.0.dist-info/METADATA
PYRP1210-1.0.0.dist-info/WHEEL
PYRP1210-1.0.0.dist-info/top_level.txt
PYRP1210-1.0.0.dist-info/RECORD
