Metadata-Version: 2.1
Name: PYRP1210
Version: 1.0.0
Summary: An RP1210 library for python
Home-page: https://github.com/Heavy-Vehicle-Networking-At-U-Tulsa/PyRP1210
Author: Jeremy Daily
Author-email: zerojw@att.net
License: UNKNOWN
Platform: UNKNOWN
Classifier: Programming Language :: Python :: 3
Classifier: License :: OSI Approved :: MIT License
